{
  "type": "File",
  "start": 0,
  "end": 371,
  "loc": {
    "start": {
      "line": 1,
      "column": 0
    },
    "end": {
      "line": 18,
      "column": 1
    }
  },
  "program": {
    "type": "Program",
    "start": 0,
    "end": 371,
    "loc": {
      "start": {
        "line": 1,
        "column": 0
      },
      "end": {
        "line": 18,
        "column": 1
      }
    },
    "sourceType": "module",
    "body": [
      {
        "type": "ImportDeclaration",
        "start": 42,
        "end": 86,
        "loc": {
          "start": {
            "line": 4,
            "column": 0
          },
          "end": {
            "line": 4,
            "column": 44
          }
        },
        "specifiers": [
          {
            "type": "ImportDefaultSpecifier",
            "start": 49,
            "end": 62,
            "loc": {
              "start": {
                "line": 4,
                "column": 7
              },
              "end": {
                "line": 4,
                "column": 20
              }
            },
            "local": {
              "type": "Identifier",
              "start": 49,
              "end": 62,
              "loc": {
                "start": {
                  "line": 4,
                  "column": 7
                },
                "end": {
                  "line": 4,
                  "column": 20
                },
                "identifierName": "createElement"
              },
              "name": "createElement",
              "leadingComments": null
            },
            "leadingComments": null
          }
        ],
        "source": {
          "type": "StringLiteral",
          "start": 68,
          "end": 85,
          "loc": {
            "start": {
              "line": 4,
              "column": 26
            },
            "end": {
              "line": 4,
              "column": 43
            }
          },
          "extra": {
            "rawValue": "./createElement",
            "raw": "'./createElement'"
          },
          "value": "./createElement"
        },
        "leadingComments": [
          {
            "type": "CommentBlock",
            "value": "*\n * Created by vincent on 17/3/11.\n ",
            "start": 0,
            "end": 41,
            "loc": {
              "start": {
                "line": 1,
                "column": 0
              },
              "end": {
                "line": 3,
                "column": 3
              }
            }
          }
        ]
      },
      {
        "type": "ImportDeclaration",
        "start": 87,
        "end": 131,
        "loc": {
          "start": {
            "line": 5,
            "column": 0
          },
          "end": {
            "line": 5,
            "column": 44
          }
        },
        "specifiers": [
          {
            "type": "ImportDefaultSpecifier",
            "start": 94,
            "end": 107,
            "loc": {
              "start": {
                "line": 5,
                "column": 7
              },
              "end": {
                "line": 5,
                "column": 20
              }
            },
            "local": {
              "type": "Identifier",
              "start": 94,
              "end": 107,
              "loc": {
                "start": {
                  "line": 5,
                  "column": 7
                },
                "end": {
                  "line": 5,
                  "column": 20
                },
                "identifierName": "DisplayObject"
              },
              "name": "DisplayObject"
            }
          }
        ],
        "source": {
          "type": "StringLiteral",
          "start": 113,
          "end": 130,
          "loc": {
            "start": {
              "line": 5,
              "column": 26
            },
            "end": {
              "line": 5,
              "column": 43
            }
          },
          "extra": {
            "rawValue": "./DisplayObject",
            "raw": "'./DisplayObject'"
          },
          "value": "./DisplayObject"
        }
      },
      {
        "type": "ExportDefaultDeclaration",
        "start": 132,
        "end": 371,
        "loc": {
          "start": {
            "line": 6,
            "column": 0
          },
          "end": {
            "line": 18,
            "column": 1
          }
        },
        "declaration": {
          "type": "ClassDeclaration",
          "start": 147,
          "end": 371,
          "loc": {
            "start": {
              "line": 6,
              "column": 15
            },
            "end": {
              "line": 18,
              "column": 1
            }
          },
          "id": {
            "type": "Identifier",
            "start": 153,
            "end": 158,
            "loc": {
              "start": {
                "line": 6,
                "column": 21
              },
              "end": {
                "line": 6,
                "column": 26
              },
              "identifierName": "Image"
            },
            "name": "Image"
          },
          "superClass": {
            "type": "Identifier",
            "start": 167,
            "end": 180,
            "loc": {
              "start": {
                "line": 6,
                "column": 35
              },
              "end": {
                "line": 6,
                "column": 48
              },
              "identifierName": "DisplayObject"
            },
            "name": "DisplayObject"
          },
          "body": {
            "type": "ClassBody",
            "start": 180,
            "end": 371,
            "loc": {
              "start": {
                "line": 6,
                "column": 48
              },
              "end": {
                "line": 18,
                "column": 1
              }
            },
            "body": [
              {
                "type": "ClassProperty",
                "start": 186,
                "end": 191,
                "loc": {
                  "start": {
                    "line": 7,
                    "column": 4
                  },
                  "end": {
                    "line": 7,
                    "column": 9
                  }
                },
                "computed": false,
                "key": {
                  "type": "Identifier",
                  "start": 186,
                  "end": 190,
                  "loc": {
                    "start": {
                      "line": 7,
                      "column": 4
                    },
                    "end": {
                      "line": 7,
                      "column": 8
                    },
                    "identifierName": "_src"
                  },
                  "name": "_src"
                },
                "static": false,
                "value": null
              },
              {
                "type": "ClassMethod",
                "start": 196,
                "end": 238,
                "loc": {
                  "start": {
                    "line": 8,
                    "column": 4
                  },
                  "end": {
                    "line": 10,
                    "column": 5
                  }
                },
                "computed": false,
                "key": {
                  "type": "Identifier",
                  "start": 200,
                  "end": 203,
                  "loc": {
                    "start": {
                      "line": 8,
                      "column": 8
                    },
                    "end": {
                      "line": 8,
                      "column": 11
                    },
                    "identifierName": "src"
                  },
                  "name": "src"
                },
                "static": false,
                "kind": "get",
                "id": null,
                "generator": false,
                "expression": false,
                "async": false,
                "params": [],
                "body": {
                  "type": "BlockStatement",
                  "start": 205,
                  "end": 238,
                  "loc": {
                    "start": {
                      "line": 8,
                      "column": 13
                    },
                    "end": {
                      "line": 10,
                      "column": 5
                    }
                  },
                  "body": [
                    {
                      "type": "ReturnStatement",
                      "start": 215,
                      "end": 232,
                      "loc": {
                        "start": {
                          "line": 9,
                          "column": 8
                        },
                        "end": {
                          "line": 9,
                          "column": 25
                        }
                      },
                      "argument": {
                        "type": "MemberExpression",
                        "start": 222,
                        "end": 231,
                        "loc": {
                          "start": {
                            "line": 9,
                            "column": 15
                          },
                          "end": {
                            "line": 9,
                            "column": 24
                          }
                        },
                        "object": {
                          "type": "ThisExpression",
                          "start": 222,
                          "end": 226,
                          "loc": {
                            "start": {
                              "line": 9,
                              "column": 15
                            },
                            "end": {
                              "line": 9,
                              "column": 19
                            }
                          }
                        },
                        "property": {
                          "type": "Identifier",
                          "start": 227,
                          "end": 231,
                          "loc": {
                            "start": {
                              "line": 9,
                              "column": 20
                            },
                            "end": {
                              "line": 9,
                              "column": 24
                            },
                            "identifierName": "_src"
                          },
                          "name": "_src"
                        },
                        "computed": false
                      }
                    }
                  ],
                  "directives": []
                }
              },
              {
                "type": "ClassMethod",
                "start": 243,
                "end": 326,
                "loc": {
                  "start": {
                    "line": 11,
                    "column": 4
                  },
                  "end": {
                    "line": 14,
                    "column": 5
                  }
                },
                "computed": false,
                "key": {
                  "type": "Identifier",
                  "start": 247,
                  "end": 250,
                  "loc": {
                    "start": {
                      "line": 11,
                      "column": 8
                    },
                    "end": {
                      "line": 11,
                      "column": 11
                    },
                    "identifierName": "src"
                  },
                  "name": "src"
                },
                "static": false,
                "kind": "set",
                "id": null,
                "generator": false,
                "expression": false,
                "async": false,
                "params": [
                  {
                    "type": "Identifier",
                    "start": 251,
                    "end": 256,
                    "loc": {
                      "start": {
                        "line": 11,
                        "column": 12
                      },
                      "end": {
                        "line": 11,
                        "column": 17
                      },
                      "identifierName": "value"
                    },
                    "name": "value"
                  }
                ],
                "body": {
                  "type": "BlockStatement",
                  "start": 257,
                  "end": 326,
                  "loc": {
                    "start": {
                      "line": 11,
                      "column": 18
                    },
                    "end": {
                      "line": 14,
                      "column": 5
                    }
                  },
                  "body": [
                    {
                      "type": "ExpressionStatement",
                      "start": 267,
                      "end": 285,
                      "loc": {
                        "start": {
                          "line": 12,
                          "column": 8
                        },
                        "end": {
                          "line": 12,
                          "column": 26
                        }
                      },
                      "expression": {
                        "type": "AssignmentExpression",
                        "start": 267,
                        "end": 284,
                        "loc": {
                          "start": {
                            "line": 12,
                            "column": 8
                          },
                          "end": {
                            "line": 12,
                            "column": 25
                          }
                        },
                        "operator": "=",
                        "left": {
                          "type": "MemberExpression",
                          "start": 267,
                          "end": 276,
                          "loc": {
                            "start": {
                              "line": 12,
                              "column": 8
                            },
                            "end": {
                              "line": 12,
                              "column": 17
                            }
                          },
                          "object": {
                            "type": "ThisExpression",
                            "start": 267,
                            "end": 271,
                            "loc": {
                              "start": {
                                "line": 12,
                                "column": 8
                              },
                              "end": {
                                "line": 12,
                                "column": 12
                              }
                            }
                          },
                          "property": {
                            "type": "Identifier",
                            "start": 272,
                            "end": 276,
                            "loc": {
                              "start": {
                                "line": 12,
                                "column": 13
                              },
                              "end": {
                                "line": 12,
                                "column": 17
                              },
                              "identifierName": "_src"
                            },
                            "name": "_src"
                          },
                          "computed": false
                        },
                        "right": {
                          "type": "Identifier",
                          "start": 279,
                          "end": 284,
                          "loc": {
                            "start": {
                              "line": 12,
                              "column": 20
                            },
                            "end": {
                              "line": 12,
                              "column": 25
                            },
                            "identifierName": "value"
                          },
                          "name": "value"
                        }
                      }
                    },
                    {
                      "type": "ExpressionStatement",
                      "start": 294,
                      "end": 320,
                      "loc": {
                        "start": {
                          "line": 13,
                          "column": 8
                        },
                        "end": {
                          "line": 13,
                          "column": 34
                        }
                      },
                      "expression": {
                        "type": "AssignmentExpression",
                        "start": 294,
                        "end": 319,
                        "loc": {
                          "start": {
                            "line": 13,
                            "column": 8
                          },
                          "end": {
                            "line": 13,
                            "column": 33
                          }
                        },
                        "operator": "=",
                        "left": {
                          "type": "MemberExpression",
                          "start": 294,
                          "end": 311,
                          "loc": {
                            "start": {
                              "line": 13,
                              "column": 8
                            },
                            "end": {
                              "line": 13,
                              "column": 25
                            }
                          },
                          "object": {
                            "type": "MemberExpression",
                            "start": 294,
                            "end": 307,
                            "loc": {
                              "start": {
                                "line": 13,
                                "column": 8
                              },
                              "end": {
                                "line": 13,
                                "column": 21
                              }
                            },
                            "object": {
                              "type": "ThisExpression",
                              "start": 294,
                              "end": 298,
                              "loc": {
                                "start": {
                                  "line": 13,
                                  "column": 8
                                },
                                "end": {
                                  "line": 13,
                                  "column": 12
                                }
                              }
                            },
                            "property": {
                              "type": "Identifier",
                              "start": 299,
                              "end": 307,
                              "loc": {
                                "start": {
                                  "line": 13,
                                  "column": 13
                                },
                                "end": {
                                  "line": 13,
                                  "column": 21
                                },
                                "identifierName": "_element"
                              },
                              "name": "_element"
                            },
                            "computed": false
                          },
                          "property": {
                            "type": "Identifier",
                            "start": 308,
                            "end": 311,
                            "loc": {
                              "start": {
                                "line": 13,
                                "column": 22
                              },
                              "end": {
                                "line": 13,
                                "column": 25
                              },
                              "identifierName": "src"
                            },
                            "name": "src"
                          },
                          "computed": false
                        },
                        "right": {
                          "type": "Identifier",
                          "start": 314,
                          "end": 319,
                          "loc": {
                            "start": {
                              "line": 13,
                              "column": 28
                            },
                            "end": {
                              "line": 13,
                              "column": 33
                            },
                            "identifierName": "value"
                          },
                          "name": "value"
                        }
                      }
                    }
                  ],
                  "directives": []
                }
              },
              {
                "type": "ClassMethod",
                "start": 331,
                "end": 369,
                "loc": {
                  "start": {
                    "line": 15,
                    "column": 4
                  },
                  "end": {
                    "line": 17,
                    "column": 5
                  }
                },
                "computed": false,
                "key": {
                  "type": "Identifier",
                  "start": 331,
                  "end": 337,
                  "loc": {
                    "start": {
                      "line": 15,
                      "column": 4
                    },
                    "end": {
                      "line": 15,
                      "column": 10
                    },
                    "identifierName": "render"
                  },
                  "name": "render"
                },
                "static": false,
                "kind": "method",
                "id": null,
                "generator": false,
                "expression": false,
                "async": false,
                "params": [],
                "body": {
                  "type": "BlockStatement",
                  "start": 339,
                  "end": 369,
                  "loc": {
                    "start": {
                      "line": 15,
                      "column": 12
                    },
                    "end": {
                      "line": 17,
                      "column": 5
                    }
                  },
                  "body": [
                    {
                      "type": "ReturnStatement",
                      "start": 349,
                      "end": 363,
                      "loc": {
                        "start": {
                          "line": 16,
                          "column": 8
                        },
                        "end": {
                          "line": 16,
                          "column": 22
                        }
                      },
                      "argument": {
                        "type": "JSXElement",
                        "start": 356,
                        "end": 362,
                        "loc": {
                          "start": {
                            "line": 16,
                            "column": 15
                          },
                          "end": {
                            "line": 16,
                            "column": 21
                          }
                        },
                        "openingElement": {
                          "type": "JSXOpeningElement",
                          "start": 356,
                          "end": 362,
                          "loc": {
                            "start": {
                              "line": 16,
                              "column": 15
                            },
                            "end": {
                              "line": 16,
                              "column": 21
                            }
                          },
                          "attributes": [],
                          "name": {
                            "type": "JSXIdentifier",
                            "start": 357,
                            "end": 360,
                            "loc": {
                              "start": {
                                "line": 16,
                                "column": 16
                              },
                              "end": {
                                "line": 16,
                                "column": 19
                              }
                            },
                            "name": "img"
                          },
                          "selfClosing": true
                        },
                        "closingElement": null,
                        "children": []
                      }
                    }
                  ],
                  "directives": []
                }
              }
            ]
          },
          "leadingComments": [],
          "trailingComments": []
        }
      }
    ],
    "directives": []
  },
  "comments": [
    {
      "type": "CommentBlock",
      "value": "*\n * Created by vincent on 17/3/11.\n ",
      "start": 0,
      "end": 41,
      "loc": {
        "start": {
          "line": 1,
          "column": 0
        },
        "end": {
          "line": 3,
          "column": 3
        }
      }
    }
  ],
  "tokens": [
    {
      "type": "CommentBlock",
      "value": "*\n * Created by vincent on 17/3/11.\n ",
      "start": 0,
      "end": 41,
      "loc": {
        "start": {
          "line": 1,
          "column": 0
        },
        "end": {
          "line": 3,
          "column": 3
        }
      }
    },
    {
      "type": {
        "label": "import",
        "keyword": "import",
        "beforeExpr": false,
        "startsExpr": false,
        "rightAssociative": false,
        "isLoop": false,
        "isAssign": false,
        "prefix": false,
        "postfix": false,
        "binop": null,
        "updateContext": null
      },
      "value": "import",
      "start": 42,
      "end": 48,
      "loc": {
        "start": {
          "line": 4,
          "column": 0
        },
        "end": {
          "line": 4,
          "column": 6
        }
      }
    },
    {
      "type": {
        "label": "name",
        "beforeExpr": false,
        "startsExpr": true,
        "rightAssociative": false,
        "isLoop": false,
        "isAssign": false,
        "prefix": false,
        "postfix": false,
        "binop": null
      },
      "value": "createElement",
      "start": 49,
      "end": 62,
      "loc": {
        "start": {
          "line": 4,
          "column": 7
        },
        "end": {
          "line": 4,
          "column": 20
        }
      }
    },
    {
      "type": {
        "label": "name",
        "beforeExpr": false,
        "startsExpr": true,
        "rightAssociative": false,
        "isLoop": false,
        "isAssign": false,
        "prefix": false,
        "postfix": false,
        "binop": null
      },
      "value": "from",
      "start": 63,
      "end": 67,
      "loc": {
        "start": {
          "line": 4,
          "column": 21
        },
        "end": {
          "line": 4,
          "column": 25
        }
      }
    },
    {
      "type": {
        "label": "string",
        "beforeExpr": false,
        "startsExpr": true,
        "rightAssociative": false,
        "isLoop": false,
        "isAssign": false,
        "prefix": false,
        "postfix": false,
        "binop": null,
        "updateContext": null
      },
      "value": "./createElement",
      "start": 68,
      "end": 85,
      "loc": {
        "start": {
          "line": 4,
          "column": 26
        },
        "end": {
          "line": 4,
          "column": 43
        }
      }
    },
    {
      "type": {
        "label": ";",
        "beforeExpr": true,
        "startsExpr": false,
        "rightAssociative": false,
        "isLoop": false,
        "isAssign": false,
        "prefix": false,
        "postfix": false,
        "binop": null,
        "updateContext": null
      },
      "start": 85,
      "end": 86,
      "loc": {
        "start": {
          "line": 4,
          "column": 43
        },
        "end": {
          "line": 4,
          "column": 44
        }
      }
    },
    {
      "type": {
        "label": "import",
        "keyword": "import",
        "beforeExpr": false,
        "startsExpr": false,
        "rightAssociative": false,
        "isLoop": false,
        "isAssign": false,
        "prefix": false,
        "postfix": false,
        "binop": null,
        "updateContext": null
      },
      "value": "import",
      "start": 87,
      "end": 93,
      "loc": {
        "start": {
          "line": 5,
          "column": 0
        },
        "end": {
          "line": 5,
          "column": 6
        }
      }
    },
    {
      "type": {
        "label": "name",
        "beforeExpr": false,
        "startsExpr": true,
        "rightAssociative": false,
        "isLoop": false,
        "isAssign": false,
        "prefix": false,
        "postfix": false,
        "binop": null
      },
      "value": "DisplayObject",
      "start": 94,
      "end": 107,
      "loc": {
        "start": {
          "line": 5,
          "column": 7
        },
        "end": {
          "line": 5,
          "column": 20
        }
      }
    },
    {
      "type": {
        "label": "name",
        "beforeExpr": false,
        "startsExpr": true,
        "rightAssociative": false,
        "isLoop": false,
        "isAssign": false,
        "prefix": false,
        "postfix": false,
        "binop": null
      },
      "value": "from",
      "start": 108,
      "end": 112,
      "loc": {
        "start": {
          "line": 5,
          "column": 21
        },
        "end": {
          "line": 5,
          "column": 25
        }
      }
    },
    {
      "type": {
        "label": "string",
        "beforeExpr": false,
        "startsExpr": true,
        "rightAssociative": false,
        "isLoop": false,
        "isAssign": false,
        "prefix": false,
        "postfix": false,
        "binop": null,
        "updateContext": null
      },
      "value": "./DisplayObject",
      "start": 113,
      "end": 130,
      "loc": {
        "start": {
          "line": 5,
          "column": 26
        },
        "end": {
          "line": 5,
          "column": 43
        }
      }
    },
    {
      "type": {
        "label": ";",
        "beforeExpr": true,
        "startsExpr": false,
        "rightAssociative": false,
        "isLoop": false,
        "isAssign": false,
        "prefix": false,
        "postfix": false,
        "binop": null,
        "updateContext": null
      },
      "start": 130,
      "end": 131,
      "loc": {
        "start": {
          "line": 5,
          "column": 43
        },
        "end": {
          "line": 5,
          "column": 44
        }
      }
    },
    {
      "type": {
        "label": "export",
        "keyword": "export",
        "beforeExpr": false,
        "startsExpr": false,
        "rightAssociative": false,
        "isLoop": false,
        "isAssign": false,
        "prefix": false,
        "postfix": false,
        "binop": null,
        "updateContext": null
      },
      "value": "export",
      "start": 132,
      "end": 138,
      "loc": {
        "start": {
          "line": 6,
          "column": 0
        },
        "end": {
          "line": 6,
          "column": 6
        }
      }
    },
    {
      "type": {
        "label": "default",
        "keyword": "default",
        "beforeExpr": true,
        "startsExpr": false,
        "rightAssociative": false,
        "isLoop": false,
        "isAssign": false,
        "prefix": false,
        "postfix": false,
        "binop": null,
        "updateContext": null
      },
      "value": "default",
      "start": 139,
      "end": 146,
      "loc": {
        "start": {
          "line": 6,
          "column": 7
        },
        "end": {
          "line": 6,
          "column": 14
        }
      }
    },
    {
      "type": {
        "label": "class",
        "keyword": "class",
        "beforeExpr": false,
        "startsExpr": false,
        "rightAssociative": false,
        "isLoop": false,
        "isAssign": false,
        "prefix": false,
        "postfix": false,
        "binop": null,
        "updateContext": null
      },
      "value": "class",
      "start": 147,
      "end": 152,
      "loc": {
        "start": {
          "line": 6,
          "column": 15
        },
        "end": {
          "line": 6,
          "column": 20
        }
      }
    },
    {
      "type": {
        "label": "name",
        "beforeExpr": false,
        "startsExpr": true,
        "rightAssociative": false,
        "isLoop": false,
        "isAssign": false,
        "prefix": false,
        "postfix": false,
        "binop": null
      },
      "value": "Image",
      "start": 153,
      "end": 158,
      "loc": {
        "start": {
          "line": 6,
          "column": 21
        },
        "end": {
          "line": 6,
          "column": 26
        }
      }
    },
    {
      "type": {
        "label": "extends",
        "keyword": "extends",
        "beforeExpr": true,
        "startsExpr": false,
        "rightAssociative": false,
        "isLoop": false,
        "isAssign": false,
        "prefix": false,
        "postfix": false,
        "binop": null,
        "updateContext": null
      },
      "value": "extends",
      "start": 159,
      "end": 166,
      "loc": {
        "start": {
          "line": 6,
          "column": 27
        },
        "end": {
          "line": 6,
          "column": 34
        }
      }
    },
    {
      "type": {
        "label": "name",
        "beforeExpr": false,
        "startsExpr": true,
        "rightAssociative": false,
        "isLoop": false,
        "isAssign": false,
        "prefix": false,
        "postfix": false,
        "binop": null
      },
      "value": "DisplayObject",
      "start": 167,
      "end": 180,
      "loc": {
        "start": {
          "line": 6,
          "column": 35
        },
        "end": {
          "line": 6,
          "column": 48
        }
      }
    },
    {
      "type": {
        "label": "{",
        "beforeExpr": true,
        "startsExpr": true,
        "rightAssociative": false,
        "isLoop": false,
        "isAssign": false,
        "prefix": false,
        "postfix": false,
        "binop": null
      },
      "start": 180,
      "end": 181,
      "loc": {
        "start": {
          "line": 6,
          "column": 48
        },
        "end": {
          "line": 6,
          "column": 49
        }
      }
    },
    {
      "type": {
        "label": "name",
        "beforeExpr": false,
        "startsExpr": true,
        "rightAssociative": false,
        "isLoop": false,
        "isAssign": false,
        "prefix": false,
        "postfix": false,
        "binop": null
      },
      "value": "_src",
      "start": 186,
      "end": 190,
      "loc": {
        "start": {
          "line": 7,
          "column": 4
        },
        "end": {
          "line": 7,
          "column": 8
        }
      }
    },
    {
      "type": {
        "label": ";",
        "beforeExpr": true,
        "startsExpr": false,
        "rightAssociative": false,
        "isLoop": false,
        "isAssign": false,
        "prefix": false,
        "postfix": false,
        "binop": null,
        "updateContext": null
      },
      "start": 190,
      "end": 191,
      "loc": {
        "start": {
          "line": 7,
          "column": 8
        },
        "end": {
          "line": 7,
          "column": 9
        }
      }
    },
    {
      "type": {
        "label": "name",
        "beforeExpr": false,
        "startsExpr": true,
        "rightAssociative": false,
        "isLoop": false,
        "isAssign": false,
        "prefix": false,
        "postfix": false,
        "binop": null
      },
      "value": "get",
      "start": 196,
      "end": 199,
      "loc": {
        "start": {
          "line": 8,
          "column": 4
        },
        "end": {
          "line": 8,
          "column": 7
        }
      }
    },
    {
      "type": {
        "label": "name",
        "beforeExpr": false,
        "startsExpr": true,
        "rightAssociative": false,
        "isLoop": false,
        "isAssign": false,
        "prefix": false,
        "postfix": false,
        "binop": null
      },
      "value": "src",
      "start": 200,
      "end": 203,
      "loc": {
        "start": {
          "line": 8,
          "column": 8
        },
        "end": {
          "line": 8,
          "column": 11
        }
      }
    },
    {
      "type": {
        "label": "(",
        "beforeExpr": true,
        "startsExpr": true,
        "rightAssociative": false,
        "isLoop": false,
        "isAssign": false,
        "prefix": false,
        "postfix": false,
        "binop": null
      },
      "start": 203,
      "end": 204,
      "loc": {
        "start": {
          "line": 8,
          "column": 11
        },
        "end": {
          "line": 8,
          "column": 12
        }
      }
    },
    {
      "type": {
        "label": ")",
        "beforeExpr": false,
        "startsExpr": false,
        "rightAssociative": false,
        "isLoop": false,
        "isAssign": false,
        "prefix": false,
        "postfix": false,
        "binop": null
      },
      "start": 204,
      "end": 205,
      "loc": {
        "start": {
          "line": 8,
          "column": 12
        },
        "end": {
          "line": 8,
          "column": 13
        }
      }
    },
    {
      "type": {
        "label": "{",
        "beforeExpr": true,
        "startsExpr": true,
        "rightAssociative": false,
        "isLoop": false,
        "isAssign": false,
        "prefix": false,
        "postfix": false,
        "binop": null
      },
      "start": 205,
      "end": 206,
      "loc": {
        "start": {
          "line": 8,
          "column": 13
        },
        "end": {
          "line": 8,
          "column": 14
        }
      }
    },
    {
      "type": {
        "label": "return",
        "keyword": "return",
        "beforeExpr": true,
        "startsExpr": false,
        "rightAssociative": false,
        "isLoop": false,
        "isAssign": false,
        "prefix": false,
        "postfix": false,
        "binop": null,
        "updateContext": null
      },
      "value": "return",
      "start": 215,
      "end": 221,
      "loc": {
        "start": {
          "line": 9,
          "column": 8
        },
        "end": {
          "line": 9,
          "column": 14
        }
      }
    },
    {
      "type": {
        "label": "this",
        "keyword": "this",
        "beforeExpr": false,
        "startsExpr": true,
        "rightAssociative": false,
        "isLoop": false,
        "isAssign": false,
        "prefix": false,
        "postfix": false,
        "binop": null,
        "updateContext": null
      },
      "value": "this",
      "start": 222,
      "end": 226,
      "loc": {
        "start": {
          "line": 9,
          "column": 15
        },
        "end": {
          "line": 9,
          "column": 19
        }
      }
    },
    {
      "type": {
        "label": ".",
        "beforeExpr": false,
        "startsExpr": false,
        "rightAssociative": false,
        "isLoop": false,
        "isAssign": false,
        "prefix": false,
        "postfix": false,
        "binop": null,
        "updateContext": null
      },
      "start": 226,
      "end": 227,
      "loc": {
        "start": {
          "line": 9,
          "column": 19
        },
        "end": {
          "line": 9,
          "column": 20
        }
      }
    },
    {
      "type": {
        "label": "name",
        "beforeExpr": false,
        "startsExpr": true,
        "rightAssociative": false,
        "isLoop": false,
        "isAssign": false,
        "prefix": false,
        "postfix": false,
        "binop": null
      },
      "value": "_src",
      "start": 227,
      "end": 231,
      "loc": {
        "start": {
          "line": 9,
          "column": 20
        },
        "end": {
          "line": 9,
          "column": 24
        }
      }
    },
    {
      "type": {
        "label": ";",
        "beforeExpr": true,
        "startsExpr": false,
        "rightAssociative": false,
        "isLoop": false,
        "isAssign": false,
        "prefix": false,
        "postfix": false,
        "binop": null,
        "updateContext": null
      },
      "start": 231,
      "end": 232,
      "loc": {
        "start": {
          "line": 9,
          "column": 24
        },
        "end": {
          "line": 9,
          "column": 25
        }
      }
    },
    {
      "type": {
        "label": "}",
        "beforeExpr": false,
        "startsExpr": false,
        "rightAssociative": false,
        "isLoop": false,
        "isAssign": false,
        "prefix": false,
        "postfix": false,
        "binop": null
      },
      "start": 237,
      "end": 238,
      "loc": {
        "start": {
          "line": 10,
          "column": 4
        },
        "end": {
          "line": 10,
          "column": 5
        }
      }
    },
    {
      "type": {
        "label": "name",
        "beforeExpr": false,
        "startsExpr": true,
        "rightAssociative": false,
        "isLoop": false,
        "isAssign": false,
        "prefix": false,
        "postfix": false,
        "binop": null
      },
      "value": "set",
      "start": 243,
      "end": 246,
      "loc": {
        "start": {
          "line": 11,
          "column": 4
        },
        "end": {
          "line": 11,
          "column": 7
        }
      }
    },
    {
      "type": {
        "label": "name",
        "beforeExpr": false,
        "startsExpr": true,
        "rightAssociative": false,
        "isLoop": false,
        "isAssign": false,
        "prefix": false,
        "postfix": false,
        "binop": null
      },
      "value": "src",
      "start": 247,
      "end": 250,
      "loc": {
        "start": {
          "line": 11,
          "column": 8
        },
        "end": {
          "line": 11,
          "column": 11
        }
      }
    },
    {
      "type": {
        "label": "(",
        "beforeExpr": true,
        "startsExpr": true,
        "rightAssociative": false,
        "isLoop": false,
        "isAssign": false,
        "prefix": false,
        "postfix": false,
        "binop": null
      },
      "start": 250,
      "end": 251,
      "loc": {
        "start": {
          "line": 11,
          "column": 11
        },
        "end": {
          "line": 11,
          "column": 12
        }
      }
    },
    {
      "type": {
        "label": "name",
        "beforeExpr": false,
        "startsExpr": true,
        "rightAssociative": false,
        "isLoop": false,
        "isAssign": false,
        "prefix": false,
        "postfix": false,
        "binop": null
      },
      "value": "value",
      "start": 251,
      "end": 256,
      "loc": {
        "start": {
          "line": 11,
          "column": 12
        },
        "end": {
          "line": 11,
          "column": 17
        }
      }
    },
    {
      "type": {
        "label": ")",
        "beforeExpr": false,
        "startsExpr": false,
        "rightAssociative": false,
        "isLoop": false,
        "isAssign": false,
        "prefix": false,
        "postfix": false,
        "binop": null
      },
      "start": 256,
      "end": 257,
      "loc": {
        "start": {
          "line": 11,
          "column": 17
        },
        "end": {
          "line": 11,
          "column": 18
        }
      }
    },
    {
      "type": {
        "label": "{",
        "beforeExpr": true,
        "startsExpr": true,
        "rightAssociative": false,
        "isLoop": false,
        "isAssign": false,
        "prefix": false,
        "postfix": false,
        "binop": null
      },
      "start": 257,
      "end": 258,
      "loc": {
        "start": {
          "line": 11,
          "column": 18
        },
        "end": {
          "line": 11,
          "column": 19
        }
      }
    },
    {
      "type": {
        "label": "this",
        "keyword": "this",
        "beforeExpr": false,
        "startsExpr": true,
        "rightAssociative": false,
        "isLoop": false,
        "isAssign": false,
        "prefix": false,
        "postfix": false,
        "binop": null,
        "updateContext": null
      },
      "value": "this",
      "start": 267,
      "end": 271,
      "loc": {
        "start": {
          "line": 12,
          "column": 8
        },
        "end": {
          "line": 12,
          "column": 12
        }
      }
    },
    {
      "type": {
        "label": ".",
        "beforeExpr": false,
        "startsExpr": false,
        "rightAssociative": false,
        "isLoop": false,
        "isAssign": false,
        "prefix": false,
        "postfix": false,
        "binop": null,
        "updateContext": null
      },
      "start": 271,
      "end": 272,
      "loc": {
        "start": {
          "line": 12,
          "column": 12
        },
        "end": {
          "line": 12,
          "column": 13
        }
      }
    },
    {
      "type": {
        "label": "name",
        "beforeExpr": false,
        "startsExpr": true,
        "rightAssociative": false,
        "isLoop": false,
        "isAssign": false,
        "prefix": false,
        "postfix": false,
        "binop": null
      },
      "value": "_src",
      "start": 272,
      "end": 276,
      "loc": {
        "start": {
          "line": 12,
          "column": 13
        },
        "end": {
          "line": 12,
          "column": 17
        }
      }
    },
    {
      "type": {
        "label": "=",
        "beforeExpr": true,
        "startsExpr": false,
        "rightAssociative": false,
        "isLoop": false,
        "isAssign": true,
        "prefix": false,
        "postfix": false,
        "binop": null,
        "updateContext": null
      },
      "value": "=",
      "start": 277,
      "end": 278,
      "loc": {
        "start": {
          "line": 12,
          "column": 18
        },
        "end": {
          "line": 12,
          "column": 19
        }
      }
    },
    {
      "type": {
        "label": "name",
        "beforeExpr": false,
        "startsExpr": true,
        "rightAssociative": false,
        "isLoop": false,
        "isAssign": false,
        "prefix": false,
        "postfix": false,
        "binop": null
      },
      "value": "value",
      "start": 279,
      "end": 284,
      "loc": {
        "start": {
          "line": 12,
          "column": 20
        },
        "end": {
          "line": 12,
          "column": 25
        }
      }
    },
    {
      "type": {
        "label": ";",
        "beforeExpr": true,
        "startsExpr": false,
        "rightAssociative": false,
        "isLoop": false,
        "isAssign": false,
        "prefix": false,
        "postfix": false,
        "binop": null,
        "updateContext": null
      },
      "start": 284,
      "end": 285,
      "loc": {
        "start": {
          "line": 12,
          "column": 25
        },
        "end": {
          "line": 12,
          "column": 26
        }
      }
    },
    {
      "type": {
        "label": "this",
        "keyword": "this",
        "beforeExpr": false,
        "startsExpr": true,
        "rightAssociative": false,
        "isLoop": false,
        "isAssign": false,
        "prefix": false,
        "postfix": false,
        "binop": null,
        "updateContext": null
      },
      "value": "this",
      "start": 294,
      "end": 298,
      "loc": {
        "start": {
          "line": 13,
          "column": 8
        },
        "end": {
          "line": 13,
          "column": 12
        }
      }
    },
    {
      "type": {
        "label": ".",
        "beforeExpr": false,
        "startsExpr": false,
        "rightAssociative": false,
        "isLoop": false,
        "isAssign": false,
        "prefix": false,
        "postfix": false,
        "binop": null,
        "updateContext": null
      },
      "start": 298,
      "end": 299,
      "loc": {
        "start": {
          "line": 13,
          "column": 12
        },
        "end": {
          "line": 13,
          "column": 13
        }
      }
    },
    {
      "type": {
        "label": "name",
        "beforeExpr": false,
        "startsExpr": true,
        "rightAssociative": false,
        "isLoop": false,
        "isAssign": false,
        "prefix": false,
        "postfix": false,
        "binop": null
      },
      "value": "_element",
      "start": 299,
      "end": 307,
      "loc": {
        "start": {
          "line": 13,
          "column": 13
        },
        "end": {
          "line": 13,
          "column": 21
        }
      }
    },
    {
      "type": {
        "label": ".",
        "beforeExpr": false,
        "startsExpr": false,
        "rightAssociative": false,
        "isLoop": false,
        "isAssign": false,
        "prefix": false,
        "postfix": false,
        "binop": null,
        "updateContext": null
      },
      "start": 307,
      "end": 308,
      "loc": {
        "start": {
          "line": 13,
          "column": 21
        },
        "end": {
          "line": 13,
          "column": 22
        }
      }
    },
    {
      "type": {
        "label": "name",
        "beforeExpr": false,
        "startsExpr": true,
        "rightAssociative": false,
        "isLoop": false,
        "isAssign": false,
        "prefix": false,
        "postfix": false,
        "binop": null
      },
      "value": "src",
      "start": 308,
      "end": 311,
      "loc": {
        "start": {
          "line": 13,
          "column": 22
        },
        "end": {
          "line": 13,
          "column": 25
        }
      }
    },
    {
      "type": {
        "label": "=",
        "beforeExpr": true,
        "startsExpr": false,
        "rightAssociative": false,
        "isLoop": false,
        "isAssign": true,
        "prefix": false,
        "postfix": false,
        "binop": null,
        "updateContext": null
      },
      "value": "=",
      "start": 312,
      "end": 313,
      "loc": {
        "start": {
          "line": 13,
          "column": 26
        },
        "end": {
          "line": 13,
          "column": 27
        }
      }
    },
    {
      "type": {
        "label": "name",
        "beforeExpr": false,
        "startsExpr": true,
        "rightAssociative": false,
        "isLoop": false,
        "isAssign": false,
        "prefix": false,
        "postfix": false,
        "binop": null
      },
      "value": "value",
      "start": 314,
      "end": 319,
      "loc": {
        "start": {
          "line": 13,
          "column": 28
        },
        "end": {
          "line": 13,
          "column": 33
        }
      }
    },
    {
      "type": {
        "label": ";",
        "beforeExpr": true,
        "startsExpr": false,
        "rightAssociative": false,
        "isLoop": false,
        "isAssign": false,
        "prefix": false,
        "postfix": false,
        "binop": null,
        "updateContext": null
      },
      "start": 319,
      "end": 320,
      "loc": {
        "start": {
          "line": 13,
          "column": 33
        },
        "end": {
          "line": 13,
          "column": 34
        }
      }
    },
    {
      "type": {
        "label": "}",
        "beforeExpr": false,
        "startsExpr": false,
        "rightAssociative": false,
        "isLoop": false,
        "isAssign": false,
        "prefix": false,
        "postfix": false,
        "binop": null
      },
      "start": 325,
      "end": 326,
      "loc": {
        "start": {
          "line": 14,
          "column": 4
        },
        "end": {
          "line": 14,
          "column": 5
        }
      }
    },
    {
      "type": {
        "label": "name",
        "beforeExpr": false,
        "startsExpr": true,
        "rightAssociative": false,
        "isLoop": false,
        "isAssign": false,
        "prefix": false,
        "postfix": false,
        "binop": null
      },
      "value": "render",
      "start": 331,
      "end": 337,
      "loc": {
        "start": {
          "line": 15,
          "column": 4
        },
        "end": {
          "line": 15,
          "column": 10
        }
      }
    },
    {
      "type": {
        "label": "(",
        "beforeExpr": true,
        "startsExpr": true,
        "rightAssociative": false,
        "isLoop": false,
        "isAssign": false,
        "prefix": false,
        "postfix": false,
        "binop": null
      },
      "start": 337,
      "end": 338,
      "loc": {
        "start": {
          "line": 15,
          "column": 10
        },
        "end": {
          "line": 15,
          "column": 11
        }
      }
    },
    {
      "type": {
        "label": ")",
        "beforeExpr": false,
        "startsExpr": false,
        "rightAssociative": false,
        "isLoop": false,
        "isAssign": false,
        "prefix": false,
        "postfix": false,
        "binop": null
      },
      "start": 338,
      "end": 339,
      "loc": {
        "start": {
          "line": 15,
          "column": 11
        },
        "end": {
          "line": 15,
          "column": 12
        }
      }
    },
    {
      "type": {
        "label": "{",
        "beforeExpr": true,
        "startsExpr": true,
        "rightAssociative": false,
        "isLoop": false,
        "isAssign": false,
        "prefix": false,
        "postfix": false,
        "binop": null
      },
      "start": 339,
      "end": 340,
      "loc": {
        "start": {
          "line": 15,
          "column": 12
        },
        "end": {
          "line": 15,
          "column": 13
        }
      }
    },
    {
      "type": {
        "label": "return",
        "keyword": "return",
        "beforeExpr": true,
        "startsExpr": false,
        "rightAssociative": false,
        "isLoop": false,
        "isAssign": false,
        "prefix": false,
        "postfix": false,
        "binop": null,
        "updateContext": null
      },
      "value": "return",
      "start": 349,
      "end": 355,
      "loc": {
        "start": {
          "line": 16,
          "column": 8
        },
        "end": {
          "line": 16,
          "column": 14
        }
      }
    },
    {
      "type": {
        "label": "jsxTagStart",
        "beforeExpr": false,
        "startsExpr": true,
        "rightAssociative": false,
        "isLoop": false,
        "isAssign": false,
        "prefix": false,
        "postfix": false,
        "binop": null
      },
      "start": 356,
      "end": 357,
      "loc": {
        "start": {
          "line": 16,
          "column": 15
        },
        "end": {
          "line": 16,
          "column": 16
        }
      }
    },
    {
      "type": {
        "label": "jsxName",
        "beforeExpr": false,
        "startsExpr": false,
        "rightAssociative": false,
        "isLoop": false,
        "isAssign": false,
        "prefix": false,
        "postfix": false,
        "binop": null,
        "updateContext": null
      },
      "value": "img",
      "start": 357,
      "end": 360,
      "loc": {
        "start": {
          "line": 16,
          "column": 16
        },
        "end": {
          "line": 16,
          "column": 19
        }
      }
    },
    {
      "type": {
        "label": "/",
        "beforeExpr": true,
        "startsExpr": false,
        "rightAssociative": false,
        "isLoop": false,
        "isAssign": false,
        "prefix": false,
        "postfix": false,
        "binop": 10,
        "updateContext": null
      },
      "value": "/",
      "start": 360,
      "end": 361,
      "loc": {
        "start": {
          "line": 16,
          "column": 19
        },
        "end": {
          "line": 16,
          "column": 20
        }
      }
    },
    {
      "type": {
        "label": "jsxTagEnd",
        "beforeExpr": false,
        "startsExpr": false,
        "rightAssociative": false,
        "isLoop": false,
        "isAssign": false,
        "prefix": false,
        "postfix": false,
        "binop": null
      },
      "start": 361,
      "end": 362,
      "loc": {
        "start": {
          "line": 16,
          "column": 20
        },
        "end": {
          "line": 16,
          "column": 21
        }
      }
    },
    {
      "type": {
        "label": ";",
        "beforeExpr": true,
        "startsExpr": false,
        "rightAssociative": false,
        "isLoop": false,
        "isAssign": false,
        "prefix": false,
        "postfix": false,
        "binop": null,
        "updateContext": null
      },
      "start": 362,
      "end": 363,
      "loc": {
        "start": {
          "line": 16,
          "column": 21
        },
        "end": {
          "line": 16,
          "column": 22
        }
      }
    },
    {
      "type": {
        "label": "}",
        "beforeExpr": false,
        "startsExpr": false,
        "rightAssociative": false,
        "isLoop": false,
        "isAssign": false,
        "prefix": false,
        "postfix": false,
        "binop": null
      },
      "start": 368,
      "end": 369,
      "loc": {
        "start": {
          "line": 17,
          "column": 4
        },
        "end": {
          "line": 17,
          "column": 5
        }
      }
    },
    {
      "type": {
        "label": "}",
        "beforeExpr": false,
        "startsExpr": false,
        "rightAssociative": false,
        "isLoop": false,
        "isAssign": false,
        "prefix": false,
        "postfix": false,
        "binop": null
      },
      "start": 370,
      "end": 371,
      "loc": {
        "start": {
          "line": 18,
          "column": 0
        },
        "end": {
          "line": 18,
          "column": 1
        }
      }
    },
    {
      "type": {
        "label": "eof",
        "beforeExpr": false,
        "startsExpr": false,
        "rightAssociative": false,
        "isLoop": false,
        "isAssign": false,
        "prefix": false,
        "postfix": false,
        "binop": null,
        "updateContext": null
      },
      "start": 371,
      "end": 371,
      "loc": {
        "start": {
          "line": 18,
          "column": 1
        },
        "end": {
          "line": 18,
          "column": 1
        }
      }
    }
  ]
}